{"name":"Awesome Set!",
 "code":"AWS",
 "border":"black",
 "booster":["land", "marketing", ["rare", "mythic rare"],"uncommon","uncommon","uncommon","common","common","common","common","common","common","common","common","common","common"],
 "cards":[
  { "layout": "split",
    "type": "Instant",
    "types": ["Instant"],
    "colors": ["Red"],
    "multiverseid": 369080,
    "names": ["Turn", "Burn"],
    "name": "Burn",
    "cmc": 2,
    "rarity": "Uncommon",
    "artist": "Ryan Barger",
    "manaCost": "{1}{R}",
    "text": "Burn deals 2 damage to target creature or player.\n\nFuse (You may cast one or both halves of this card from your hand.)",
    "number": "134b",
    "imageName": "turnburn"
  },
  { "layout":"normal",
    "name":"Academy Raider",
    "type": "Creature — Human Warrior",
    "types":["Creature"],
    "subtypes":["human","warrior"],
    "colors":["red"],
    "cmc":3,
    "manaCost":"{2}{R}",
    "text":"Intimidate (This creature can't be blocked except by artifact creatures and/or creatures that share a color with it.)\n\nWhenever Academy Raider deals combat damage to a player, you may discard a card. If you do, draw a card.",
    "power":"1",
    "toughness":"1",
    "rarity":"Common",
    "imageName":"academy raider",
    "artist":"Karl Kopinski",
    "cardCode":"CR01",
    "multiverseid":12345,
    "editURL":"http://multiverse.example.com/cards/12345"},
  { "layout": "split",
    "type": "Instant",
    "types": ["Instant"],
    "colors": ["Blue"],
    "multiverseid": 369080,
    "names": ["Turn", "Burn"],
    "name": "Turn",
    "cmc": 3,
    "rarity": "Uncommon",
    "artist": "Ryan Barger",
    "manaCost": "{2}{U}",
    "text": "Target creature loses all abilities and becomes a 0/1 red Weird until end of turn.\n\nFuse (You may cast one or both halves of this card from your hand.)",
    "number": "134a",
    "imageName": "turnburn"
  },
  { "layout": "split",
    "type": "Sorcery",
    "types": ["Sorcery"],
    "colors": ["Green"],
    "multiverseid": 369041,
    "names": ["Alive", "Well"],
    "name": "Alive",
    "cmc": 4,
    "rarity": "Uncommon",
    "artist": "Nils Hamm",
    "manaCost": "{3}{G}",
    "text": "Put a 3/3 green Centaur creature token onto the battlefield.\n\nFuse (You may cast one or both halves of this card from your hand.)",
    "number": "121a",
    "imageName": "alivewell"
  },
  { "layout": "split",
    "type": "Sorcery",
    "types": ["Sorcery"],
    "colors": ["White"],
    "multiverseid": 369041,
    "names": ["Alive", "Well"],
    "name": "Well",
    "cmc": 1,
    "rarity": "Uncommon",
    "artist": "Nils Hamm",
    "manaCost": "{W}",
    "text": "You gain 2 life for each creature you control.\n\nFuse (You may cast one or both halves of this card from your hand.)",
    "number": "121b",
    "imageName": "alivewell"
  }
]}